pycodehealth/__init__.py
pycodehealth/_version.py
pycodehealth/cli.py
pycodehealth/utils.py
pycodehealth-0.0.1b0.dist-info/METADATA
pycodehealth-0.0.1b0.dist-info/WHEEL
pycodehealth-0.0.1b0.dist-info/entry_points.txt
pycodehealth-0.0.1b0.dist-info/top_level.txt
pycodehealth-0.0.1b0.dist-info/RECORD
