Metadata-Version: 2.1
Name: pycodehealth
Version: 0.0.1b0
Summary: PyCodeHealth is a Python package for high-quality code maintenance, providing Static Code Analysis tools, automatic formatting, and a web-based Dashboard. It streamlines workflow and improves code quality, allowing users to choose their preferred linter, type checker, and formatting tool.
Author: Ricardo Leal
Author-email: rick.leal420@gmail.com
Maintainer: Ricardo Leal
Maintainer-email: ricardo.lealpz@gmail.com
License: MIT
Project-URL: Bug Reports, https://github.com/ricardoleal20/PyCodeHealth/issues
Classifier: Development Status :: 4 - Beta
Classifier: Environment :: Console
Classifier: Intended Audience :: Developers
Classifier: Operating System :: MacOS :: MacOS X
Classifier: Operating System :: Microsoft :: Windows
Classifier: Operating System :: POSIX
Classifier: Programming Language :: Python
Classifier: Programming Language :: Python :: 3
Classifier: Programming Language :: Python :: 3.8
Classifier: Programming Language :: Python :: 3.9
Classifier: Programming Language :: Python :: 3.10
Classifier: Programming Language :: Python :: 3.11
Classifier: Topic :: Software Development
Requires-Python: >=3.8, <4
Requires-Dist: click (>=8.1)
Requires-Dist: attrs (>=22.1.0)
Requires-Dist: rich (>=2.6)
Requires-Dist: pylint (>=2.15)
